clustering_afe/__init__.py
clustering_afe/automated_clustering.py
clustering_afe/component_normalization.py
clustering_afe/data_cleaning.py
clustering_afe/feature_reduction.py
clustering_afe/feature_transformation.py
clustering_afe/gpt_transformation.py
clustering_afe/main_pipeline_orchestrator.py
clustering_afe/visualize_clustering.py
tests/__init__.py
tests/test_data_cleaning.py
tests/test_feature_reduction.py
tests/test_feature_transformation.py
tests/test_gpt_transformation.py
clustering_afe-1.1.9.dist-info/LICENSE
clustering_afe-1.1.9.dist-info/LICENSE.txt
clustering_afe-1.1.9.dist-info/METADATA
clustering_afe-1.1.9.dist-info/WHEEL
clustering_afe-1.1.9.dist-info/top_level.txt
clustering_afe-1.1.9.dist-info/RECORD
